{
	"instance" : {
		"lowtalkPerform:withArguments:inSuperclass:node:" : "RonieSalgado 5/25/2017 03:38",
		"environment" : "RonieSalgado 5/24/2017 02:44",
		"value:value:value:" : "RonieSalgado 5/24/2017 02:45",
		"value:value:" : "RonieSalgado 5/24/2017 02:45",
		"value:value:value:value:value:" : "RonieSalgado 5/24/2017 02:45",
		"value" : "RonieSalgado 5/24/2017 02:45",
		"value:" : "RonieSalgado 5/24/2017 02:45",
		"lowtalkValueWithArguments:types:compiler:at:" : "RonieSalgado 5/24/2017 02:46",
		"definition" : "RonieSalgado 5/24/2017 02:44",
		"definition:" : "RonieSalgado 5/24/2017 02:44",
		"environment:" : "RonieSalgado 5/24/2017 02:44",
		"valueWithArguments:" : "RonieSalgado 5/24/2017 02:45",
		"value:value:value:value:" : "RonieSalgado 5/24/2017 02:45"
	},
	"class" : {
		"initialize" : "RonieSalgado 5/25/2017 03:36"
	}
}